{
  "sharedDir": "shared",
  "dependenciesDir": "extern",
  "info": {
    "name": "Noodle Extensions",
    "id": "NoodleExtensions",
    "version": "0.2.2",
    "url": null,
    "additionalData": {}
  },
  "dependencies": [
    {
      "id": "beatsaber-hook",
      "versionRange": "^2.2.2",
      "additionalData": {
        "extraFiles": [
          "src/inline-hook"
        ]
      }
    },
    {
      "id": "codegen",
      "versionRange": "^0.12.5",
      "additionalData": {}
    },
    {
      "id": "custom-types",
      "versionRange": "^0.12.5",
      "additionalData": {}
    },
    {
      "id": "custom-json-data",
      "versionRange": "^0.11.0",
      "additionalData": {}
    },
    {
      "id": "questui",
      "versionRange": "^0.10.1",
      "additionalData": {}
    },
    {
      "id": "config-utils",
      "versionRange": "^0.5.1",
      "additionalData": {}
    }
  ],
  "additionalData": {}
}